Workbook
Name aporte: 'Simulador'!$B$6
Name qtd_anos: 'Simulador'!$B$7
Name taxa_mensal: 'Simulador'!$B$8
Name patrimonio: 'Simulador'!$B$12
Name salario: 'Configuracoes'!$B$5
Name rendimento_carteira: 'Configuracoes'!$B$6
Name sugestao_investimento: 'Configuracoes'!$B$8

Sheet Simulador
A1: SIMULADOR DE FUNDOS IMOBILIÁRIOS
A3: Planejamento ilustrativo de aportes, patrimônio futuro e distribuição por perfil
A5: PARÂMETROS DA SIMULAÇÃO | G5: CONFIGURAÇÕES DE REFERÊNCIA
A6: Aporte mensal (R$) | B6: 200 | C6: Edite as células amarelas | G6: Salário de exemplo | H6: =salario
A7: Prazo (anos) | B7: 5 | C7: Use prazo de 1 a 50 anos | G7: Sugestão de aporte (30%) | H7: =sugestao_investimento
A8: Rendimento mensal estimado | B8: 0.01079 | C8: Taxa constante hipotética | G8: Rendimento da carteira | H8: =rendimento_carteira
A9: Perfil de distribuição | B9: Moderado | C9: A lista altera os percentuais | G9: Nota | H9: Parâmetros na aba Configuracoes
A11: RESULTADOS PRINCIPAIS
A12: Patrimônio projetado | B12: =FV(taxa_mensal,qtd_anos*12,-aporte,0,0)
A13: Dividendos mensais estimados | B13: =patrimonio*rendimento_carteira
A14: Total de aportes | B14: =aporte*qtd_anos*12
A15: Ganho projetado estimado | B15: =patrimonio-(aporte*qtd_anos*12)
A18: DISTRIBUIÇÃO DO APORTE POR TIPO DE FII
A19: Tipo de FII | B19: Percentual | C19: Aporte mensal (R$)
A20: PAPEL | B20: =IFERROR(VLOOKUP($B$9&"-"&A20,Apoio!$A$3:$D$20,4,FALSE),0) | C20: =B20*aporte
A21: TIJOLO | B21: =IFERROR(VLOOKUP($B$9&"-"&A21,Apoio!$A$3:$D$20,4,FALSE),0) | C21: =B21*aporte
A22: HÍBRIDOS | B22: =IFERROR(VLOOKUP($B$9&"-"&A22,Apoio!$A$3:$D$20,4,FALSE),0) | C22: =B22*aporte
A23: FOFs | B23: =IFERROR(VLOOKUP($B$9&"-"&A23,Apoio!$A$3:$D$20,4,FALSE),0) | C23: =B23*aporte
A24: DESENVOLVIMENTO | B24: =IFERROR(VLOOKUP($B$9&"-"&A24,Apoio!$A$3:$D$20,4,FALSE),0) | C24: =B24*aporte
A25: HOTELARIAS | B25: =IFERROR(VLOOKUP($B$9&"-"&A25,Apoio!$A$3:$D$20,4,FALSE),0) | C25: =B25*aporte
A26: TOTAL | B26: =SUM(B20:B25) | C26: =SUM(C20:C25)
A29: CENÁRIOS DE LONGO PRAZO
A30: Prazo (anos) | B30: Meses | C30: Total aportado | D30: Patrimônio projetado | E30: Dividendos/mês estimados
A31: 2 | B31: =A31*12 | C31: =aporte*B31 | D31: =FV(taxa_mensal,B31,-aporte,0,0) | E31: =D31*rendimento_carteira
A32: 5 | B32: =A32*12 | C32: =aporte*B32 | D32: =FV(taxa_mensal,B32,-aporte,0,0) | E32: =D32*rendimento_carteira
A33: 10 | B33: =A33*12 | C33: =aporte*B33 | D33: =FV(taxa_mensal,B33,-aporte,0,0) | E33: =D33*rendimento_carteira
A34: 20 | B34: =A34*12 | C34: =aporte*B34 | D34: =FV(taxa_mensal,B34,-aporte,0,0) | E34: =D34*rendimento_carteira
A35: 30 | B35: =A35*12 | C35: =aporte*B35 | D35: =FV(taxa_mensal,B35,-aporte,0,0) | E35: =D35*rendimento_carteira
A38: Simulação educacional: pressupõe taxa mensal constante e aportes no fim de cada mês. Os rendimentos reais dos FIIs variam; esta projeção não é garantia nem recomendação de investimento.

Sheet Configuracoes
A1: CONFIGURAÇÕES E PREMISSAS
A4: Parâmetro | B4: Valor de exemplo | C4: Descrição
A5: Salário mensal | B5: 2000 | C5: Valor fictício utilizado para demonstrar a sugestão de aporte.
A6: Rendimento da carteira (mensal) | B6: 0.006 | C6: Taxa hipotética usada para estimar dividendos mensais sobre o patrimônio.
A7: Percentual sugerido de aporte | B7: 0.3 | C7: Premissa didática de 30% do salário; não é recomendação financeira.
A8: Sugestão de investimento | B8: =B5*B7 | C8: Resultado calculado: salário multiplicado pelo percentual sugerido.
A10: Observação | B10: Todos os números são fictícios e servem apenas para demonstrar o funcionamento da planilha. Ajuste as premissas com cautela.

Sheet Apoio
A1: TABELA DE DISTRIBUIÇÃO POR PERFIL
A2: Chave composta | B2: Perfil | C2: Tipo de FII | D2: Percentual | F2: Conferência dos perfis | G2: Total
A3: =B3&"-"&C3 | B3: Conservador | C3: PAPEL | D3: 0.3 | F3: Conservador | G3: =SUMIF($B$3:$B$20,F3,$D$3:$D$20)
A4: =B4&"-"&C4 | B4: Conservador | C4: TIJOLO | D4: 0.5 | F4: Moderado | G4: =SUMIF($B$3:$B$20,F4,$D$3:$D$20)
A5: =B5&"-"&C5 | B5: Conservador | C5: HÍBRIDOS | D5: 0.1 | F5: Agressivo | G5: =SUMIF($B$3:$B$20,F5,$D$3:$D$20)
A6: =B6&"-"&C6 | B6: Conservador | C6: FOFs | D6: 0.1
A7: =B7&"-"&C7 | B7: Conservador | C7: DESENVOLVIMENTO | D7: 0
A8: =B8&"-"&C8 | B8: Conservador | C8: HOTELARIAS | D8: 0 | F8: Os percentuais foram adaptados da tabela de referência do arquivo do Expert fornecido no desafio. São exemplos didáticos, não recomendação de investimento.
A9: =B9&"-"&C9 | B9: Moderado | C9: PAPEL | D9: 0.32
A10: =B10&"-"&C10 | B10: Moderado | C10: TIJOLO | D10: 0.35
A11: =B11&"-"&C11 | B11: Moderado | C11: HÍBRIDOS | D11: 0.08
A12: =B12&"-"&C12 | B12: Moderado | C12: FOFs | D12: 0.05
A13: =B13&"-"&C13 | B13: Moderado | C13: DESENVOLVIMENTO | D13: 0.1
A14: =B14&"-"&C14 | B14: Moderado | C14: HOTELARIAS | D14: 0.1
A15: =B15&"-"&C15 | B15: Agressivo | C15: PAPEL | D15: 0.5
A16: =B16&"-"&C16 | B16: Agressivo | C16: TIJOLO | D16: 0.1
A17: =B17&"-"&C17 | B17: Agressivo | C17: HÍBRIDOS | D17: 0.05
A18: =B18&"-"&C18 | B18: Agressivo | C18: FOFs | D18: 0.05
A19: =B19&"-"&C19 | B19: Agressivo | C19: DESENVOLVIMENTO | D19: 0.2
A20: =B20&"-"&C20 | B20: Agressivo | C20: HOTELARIAS | D20: 0.1
